AUTHORS.txt
CHANGES.txt
CONTRIBUTORS.txt
LICENSE.txt
MANIFEST.in
README.txt
setup.cfg
setup.py
lib/Scripy.egg-info/PKG-INFO
lib/Scripy.egg-info/SOURCES.txt
lib/Scripy.egg-info/dependency_links.txt
lib/Scripy.egg-info/requires.txt
lib/Scripy.egg-info/top_level.txt
lib/Scripy.egg-info/zip-safe
lib/scripy/__init__.py
lib/scripy/_config.py
lib/scripy/_path.py
lib/scripy/edit.py
lib/scripy/shell.py
lib/scripy/system.py
lib/scripy/setup/__init__.py
lib/scripy/setup/config.py
test/__init__.py
test/test_edit.py
test/test_shell.py