Metadata-Version: 1.0
Name: Scripy
Version: 0.9.3
Summary: Python tools for manage system commands as replacement to bash script
Home-page: http://bitbucket.org/ares/scripy/
Author: Jonas Melian
Author-email: jonas@mailup.net
License: UNKNOWN
Keywords: system shell command bash administration
Platform: UNKNOWN
Classifier: Development Status :: 4 - Beta
Classifier: Environment :: Console
Classifier: Intended Audience :: Developers
Classifier: Intended Audience :: System Administrators
Classifier: License :: OSI Approved :: ISC License (ISCL)
Classifier: Natural Language :: English
Classifier: Operating System :: POSIX
Classifier: Operating System :: POSIX :: Linux
Classifier: Programming Language :: Python :: 2.6
Classifier: Topic :: System :: Systems Administration
Classifier: Topic :: System :: System Shells
